chronofidelius/__init__.py
chronofidelius/main.py
chronofidelius/unigram_frequencies.py
chronofidelius/char_freqs/cz_char_freqs_dict.pkl
chronofidelius/char_freqs/de_char_freqs_dict.pkl
chronofidelius/char_freqs/el_char_freqs_dict.pkl
chronofidelius/char_freqs/en_char_freqs_dict.pkl
chronofidelius/char_freqs/es_char_freqs_dict.pkl
chronofidelius/char_freqs/fr_char_freqs_dict.pkl
chronofidelius/char_freqs/hu_char_freqs_dict.pkl
chronofidelius/char_freqs/is_char_freqs_dict.pkl
chronofidelius/char_freqs/it_char_freqs_dict.pkl
chronofidelius/char_freqs/la_char_freqs_dict.pkl
chronofidelius/char_freqs/nl_char_freqs_dict.pkl
chronofidelius/char_freqs/pl_char_freqs_dict.pkl
chronofidelius/char_freqs/ru_char_freqs_dict.pkl
chronofidelius/char_freqs/sl_char_freqs_dict.pkl
chronofidelius/char_freqs/sv_char_freqs_dict.pkl
chronofidelius-1.1.2.dist-info/licenses/LICENSE
chronofidelius-1.1.2.dist-info/METADATA
chronofidelius-1.1.2.dist-info/WHEEL
chronofidelius-1.1.2.dist-info/top_level.txt
chronofidelius-1.1.2.dist-info/RECORD
