Metadata-Version: 2.4
Name: ChronoFidelius
Version: 1.1.2
Summary: A Python library for for plaintext encryption using homophonic substitution and historical character frequencies.
Home-page: https://github.com/mbruton0426/ChronoFidelius
Author: Micaella Bruton
Author-email: micaella.bruton@ling.su.se
License: Apache License 2.0
Classifier: Programming Language :: Python :: 3
Classifier: License :: OSI Approved :: Apache Software License
Classifier: Operating System :: OS Independent
Requires-Python: >=3.6
License-File: LICENSE
Dynamic: author
Dynamic: author-email
Dynamic: classifier
Dynamic: description
Dynamic: description-content-type
Dynamic: home-page
Dynamic: license
Dynamic: license-file
Dynamic: requires-python
Dynamic: summary
